mosaic_materials/__init__.py
mosaic_materials/engine.py
mosaic_materials/constraints/__init__.py
mosaic_materials/constraints/constraint.py
mosaic_materials/constraints/energy.py
mosaic_materials/constraints/neutron.py
mosaic_materials/constraints/rdf.py
mosaic_materials/constraints/total_scattering.py
mosaic_materials/constraints/xray.py
mosaic_materials/data/__init__.py
mosaic_materials/data/total_scattering.py
mosaic_materials/misc/__init__.py
mosaic_materials/misc/plot.py
mosaic_materials/monte_carlo/__init__.py
mosaic_materials/monte_carlo/adapt.py
mosaic_materials/monte_carlo/callbacks.py
mosaic_materials/monte_carlo/criteria.py
mosaic_materials/monte_carlo/driver.py
mosaic_materials/monte_carlo/schedules.py
mosaic_materials/monte_carlo/trajectory.py
mosaic_materials/moves/__init__.py
mosaic_materials/moves/move.py
mosaic_materials/moves/rotate.py
mosaic_materials/moves/translate.py
mosaic_materials/moves/translate_rotate.py
mosaic_materials/moves/utils.py
mosaic_materials/moves/volume.py
mosaic_materials/state/__init__.py
mosaic_materials/state/composition.py
mosaic_materials/state/state.py
mosaic_materials/state/styles.py
mosaic_materials/state/system.py
mosaic_materials-0.1.3.dist-info/licenses/LICENSE
mosaic_materials-0.1.3.dist-info/METADATA
mosaic_materials-0.1.3.dist-info/WHEEL
mosaic_materials-0.1.3.dist-info/top_level.txt
mosaic_materials-0.1.3.dist-info/RECORD
