Metadata-Version: 2.4
Name: mosaic-materials
Version: 0.1.3
Summary: Monte-Carlo optimisation with scattering and interatomic-potential constraints for materials.
Author-email: "Thomas C. Nicholas" <tcnicholas@me.com>
License: MIT License
Project-URL: Homepage, https://github.com/tcnicholas/mosaic-materials
Project-URL: Issues, https://github.com/tcnicholas/mosaic-materials/issues
Project-URL: Documentation, https://tcnicholas.github.io/mosaic-materials
Project-URL: Changelog, https://github.com/tcnicholas/mosaic-materials/releases
Classifier: Development Status :: 3 - Alpha
Classifier: Intended Audience :: Science/Research
Classifier: License :: OSI Approved :: MIT License
Classifier: Programming Language :: Python :: 3
Classifier: Programming Language :: Python :: 3 :: Only
Classifier: Programming Language :: Python :: 3.9
Classifier: Programming Language :: Python :: 3.10
Classifier: Programming Language :: Python :: 3.11
Classifier: Programming Language :: Python :: 3.12
Classifier: Topic :: Scientific/Engineering
Classifier: Operating System :: OS Independent
Requires-Python: >=3.9
License-File: LICENSE
Requires-Dist: ase>=3.26.0
Requires-Dist: numba>=0.60.0
Requires-Dist: pylammpsmpi>=0.2.39
Provides-Extra: tests
Requires-Dist: pytest; extra == "tests"
Requires-Dist: pytest-cov; extra == "tests"
Provides-Extra: dev
Requires-Dist: bumpver; extra == "dev"
Requires-Dist: ruff; extra == "dev"
Provides-Extra: publish
Requires-Dist: build; extra == "publish"
Requires-Dist: twine; extra == "publish"
Dynamic: license-file
